opus_api/__init__.py
opus_api/cache.py
opus_api/cli.py
opus_api/crawler.py
opus_api/exceptions.py
opus_api/opus_api.py
opus_api/settings.py
opus_api/util.py
opus_api-0.6.2.dist-info/METADATA
opus_api-0.6.2.dist-info/RECORD
opus_api-0.6.2.dist-info/WHEEL
opus_api-0.6.2.dist-info/entry_points.txt
opus_api-0.6.2.dist-info/top_level.txt
