Metadata-Version: 1.1
Name: opus_api
Version: 0.6.2
Summary: OPUS (opus.nlpl.eu) Python API
Home-page: https://github.com/yonkornilov/opus-api
Author: Yonathan Koren
Author-email: yonkornilov@live.com
License: MIT license
Keywords: opus_api,api,parallel,corpora,mmt
Platform: UNKNOWN
Classifier: Development Status :: 4 - Beta
Classifier: Intended Audience :: Developers
Classifier: License :: OSI Approved :: MIT License
Classifier: Natural Language :: English
Classifier: Programming Language :: Python :: 3.5
